drillcore_transformations/__init__.py
drillcore_transformations/transformations.py
drillcore_transformations/utils.py
drillcore_transformations/tests/__init__.py
drillcore_transformations/tests/test_convention.py
drillcore_transformations/tests/test_transformations.py
drillcore_transformations-0.3.0.dist-info/licenses/LICENSE
drillcore_transformations-0.3.0.dist-info/METADATA
drillcore_transformations-0.3.0.dist-info/WHEEL
drillcore_transformations-0.3.0.dist-info/top_level.txt
drillcore_transformations-0.3.0.dist-info/RECORD
