Metadata-Version: 2.4
Name: drillcore-transformations
Version: 0.3.0
Summary: Transform structural drillcore measurements.
Author-email: nialov <nikolasovaskainen@gmail.com>
License-Expression: MIT
Project-URL: Homepage, https://github.com/nialov/drillcore-transformations
Project-URL: Repository, https://github.com/nialov/drillcore-transformations
Classifier: Programming Language :: Python :: 3 :: Only
Requires-Python: >=3.9
License-File: LICENSE
Requires-Dist: numpy
Provides-Extra: test
Requires-Dist: pytest; extra == "test"
Requires-Dist: hypothesis; extra == "test"
Requires-Dist: mypy; extra == "test"
Provides-Extra: docs
Requires-Dist: pandas; extra == "docs"
Requires-Dist: marimo; extra == "docs"
Requires-Dist: nbformat; extra == "docs"
Requires-Dist: matplotlib; extra == "docs"
Dynamic: license-file
